stowin_py/__init__.py
stowin_py/cli.py
stowin_py-0.1.0.dist-info/METADATA
stowin_py-0.1.0.dist-info/WHEEL
stowin_py-0.1.0.dist-info/entry_points.txt
stowin_py-0.1.0.dist-info/licenses/LICENSE
stowin_py-0.1.0.dist-info/RECORD
