Metadata-Version: 2.4
Name: stowin-py
Version: 0.1.0
Summary: A GNU Stow alternative in Python
Project-URL: Homepage, https://github.com/yourusername/stowin-py
Author-email: Your Name <kmuthish@gmail.com>
License: MIT License
License-File: LICENSE
Keywords: dotfiles,stow,symlink
Classifier: License :: OSI Approved :: MIT License
Classifier: Programming Language :: Python
Classifier: Programming Language :: Python :: 3
Requires-Python: >=3.9
Requires-Dist: click>=8.0.0
Requires-Dist: tqdm>=4.65.0
